jqtui/__init__.py
jqtui/jqtui.css
jqtui/jqtui.py
jqtui-0.0.3.dist-info/LICENSE
jqtui-0.0.3.dist-info/METADATA
jqtui-0.0.3.dist-info/WHEEL
jqtui-0.0.3.dist-info/entry_points.txt
jqtui-0.0.3.dist-info/RECORD
